scikit_visualizations-0.1.6.dist-info/METADATA
scikit_visualizations-0.1.6.dist-info/RECORD
scikit_visualizations-0.1.6.dist-info/WHEEL
scikit_visualizations-0.1.6.dist-info/top_level.txt
skvisualizations/__init__.py
skvisualizations/scores.py
skvisualizations/validation.py
tests/__init__.py
tests/test_scores.py
tests/test_validation.py
