Metadata-Version: 2.1
Name: scikit-visualizations
Version: 0.1.6
Summary: Scikit-learn-compatible visualizations
Home-page: https://github.com/daviddiazvico/scikit-visualizations
Author: David Diaz Vico
Author-email: david.diaz.vico@outlook.com
License: UNKNOWN
Download-URL: https://github.com/daviddiazvico/scikit-visualizations/archive/v0.1.6.tar.gz
Keywords: scikit-learn,keras,pandas,scipy,seaborn
Platform: UNKNOWN
Classifier: Intended Audience :: Science/Research
Classifier: Intended Audience :: Developers
Classifier: Topic :: Software Development
Classifier: Topic :: Scientific/Engineering
Classifier: Programming Language :: Python
Classifier: Programming Language :: Python :: 2
Classifier: Programming Language :: Python :: 2.7
Classifier: Programming Language :: Python :: 3
Classifier: Programming Language :: Python :: 3.5
Classifier: Programming Language :: Python :: 3.6
Requires-Dist: pandas
Requires-Dist: scikit-learn
Requires-Dist: seaborn
